nailgun_net_check-8.0.17.dev3869.dist-info/RECORD
nailgun_net_check-8.0.17.dev3869.dist-info/pbr.json
nailgun_net_check-8.0.17.dev3869.dist-info/DESCRIPTION.rst
nailgun_net_check-8.0.17.dev3869.dist-info/top_level.txt
nailgun_net_check-8.0.17.dev3869.dist-info/WHEEL
nailgun_net_check-8.0.17.dev3869.dist-info/metadata.json
nailgun_net_check-8.0.17.dev3869.dist-info/entry_points.txt
nailgun_net_check-8.0.17.dev3869.dist-info/METADATA
network_checker/config.py
network_checker/api.py
network_checker/__init__.py
network_checker/daemon.py
network_checker/xmlrpc.py
network_checker/cli.py
network_checker/multicast/api.py
network_checker/multicast/__init__.py
network_checker/net_check/api.py
network_checker/net_check/__init__.py
network_checker/net_check/utils.py
network_checker/tests/simple.py
network_checker/tests/__init__.py
network_checker/tests/test_net_check.py
network_checker/tests/test_multicast.py
dhcp_checker/api.py
dhcp_checker/__init__.py
dhcp_checker/commands.py
dhcp_checker/cli.py
dhcp_checker/utils.py
