Metadata-Version: 2.0
Name: nailgun-net-check
Version: 8.0.17.dev3869
Summary: Nailgun Network Checker
Home-page: http://www.openstack.org/
Author: Dmitry Pyzhov
Author-email: dpyzhov@mirantis.com
License: Apache License, Version 2.0
Platform: UNKNOWN
Classifier: Environment :: OpenStack
Classifier: Intended Audience :: Information Technology
Classifier: Intended Audience :: System Administrators
Classifier: License :: OSI Approved :: Apache Software License
Classifier: Operating System :: POSIX :: Linux
Classifier: Programming Language :: Python
Classifier: Programming Language :: Python :: 2
Classifier: Programming Language :: Python :: 2.7
Classifier: Programming Language :: Python :: 2.6
Classifier: Programming Language :: Python :: 3
Classifier: Programming Language :: Python :: 3.4
Requires-Dist: pbr (>=1.6)
Requires-Dist: argparse
Requires-Dist: cliff-tablib
Requires-Dist: scapy (==2.2.0-dev)
Requires-Dist: pypcap (==1.1.1)
Requires-Dist: stevedore
Requires-Dist: daemonize
Requires-Dist: pyyaml
Requires-Dist: requests
Requires-Dist: netifaces
Requires-Dist: six
